bilirpc/__init__.py
bilirpc/api.py
bilirpc/bilibili/__init__.py
bilirpc/bilibili/account/fission/v1/fission.proto
bilirpc/bilibili/account/fission/v1/fission_pb2.py
bilirpc/bilibili/account/fission/v1/fission_pb2_grpc.py
bilirpc/bilibili/ad/v1/ad.proto
bilirpc/bilibili/ad/v1/ad_pb2.py
bilirpc/bilibili/ad/v1/ad_pb2_grpc.py
bilirpc/bilibili/api/player/v1/player.proto
bilirpc/bilibili/api/player/v1/player_pb2.py
bilirpc/bilibili/api/player/v1/player_pb2_grpc.py
bilirpc/bilibili/api/probe/v1/probe.proto
bilirpc/bilibili/api/probe/v1/probe_pb2.py
bilirpc/bilibili/api/probe/v1/probe_pb2_grpc.py
bilirpc/bilibili/app/archive/middleware/v1/preload.proto
bilirpc/bilibili/app/archive/middleware/v1/preload_pb2.py
bilirpc/bilibili/app/archive/middleware/v1/preload_pb2_grpc.py
bilirpc/bilibili/app/archive/v1/archive.proto
bilirpc/bilibili/app/archive/v1/archive_pb2.py
bilirpc/bilibili/app/archive/v1/archive_pb2_grpc.py
bilirpc/bilibili/app/card/v1/ad.proto
bilirpc/bilibili/app/card/v1/ad_pb2.py
bilirpc/bilibili/app/card/v1/ad_pb2_grpc.py
bilirpc/bilibili/app/card/v1/card.proto
bilirpc/bilibili/app/card/v1/card_pb2.py
bilirpc/bilibili/app/card/v1/card_pb2_grpc.py
bilirpc/bilibili/app/card/v1/common.proto
bilirpc/bilibili/app/card/v1/common_pb2.py
bilirpc/bilibili/app/card/v1/common_pb2_grpc.py
bilirpc/bilibili/app/card/v1/double.proto
bilirpc/bilibili/app/card/v1/double_pb2.py
bilirpc/bilibili/app/card/v1/double_pb2_grpc.py
bilirpc/bilibili/app/card/v1/single.proto
bilirpc/bilibili/app/card/v1/single_pb2.py
bilirpc/bilibili/app/card/v1/single_pb2_grpc.py
bilirpc/bilibili/app/click/v1/heartbeat.proto
bilirpc/bilibili/app/click/v1/heartbeat_pb2.py
bilirpc/bilibili/app/click/v1/heartbeat_pb2_grpc.py
bilirpc/bilibili/app/distribution/setting/download.proto
bilirpc/bilibili/app/distribution/setting/download_pb2.py
bilirpc/bilibili/app/distribution/setting/download_pb2_grpc.py
bilirpc/bilibili/app/distribution/setting/dynamic.proto
bilirpc-1.5.dist-info/METADATA
bilirpc-1.5.dist-info/WHEEL
bilirpc-1.5.dist-info/RECORD
