Metadata-Version: 2.1
Name: bilirpc
Version: 1.5
Summary: B站grpc请求2
License: MIT
Author: Polyisoprene
Author-email: lzxder@outlook.com
Requires-Python: >=3.8,<4.0
Classifier: License :: OSI Approved :: MIT License
Classifier: Programming Language :: Python :: 3
Classifier: Programming Language :: Python :: 3.8
Classifier: Programming Language :: Python :: 3.9
Classifier: Programming Language :: Python :: 3.10
Classifier: Programming Language :: Python :: 3.11
Requires-Dist: grpcio (>=1.56.2,<2.0.0)
Requires-Dist: grpcio-tools (>=1.56.2,<2.0.0)
Requires-Dist: loguru (>=0.7.0,<0.8.0)
Requires-Dist: protobuf (>=4.23.4,<5.0.0)
